worker/__init__.py
pythreadworker-0.10.0.dist-info/METADATA
pythreadworker-0.10.0.dist-info/WHEEL
pythreadworker-0.10.0.dist-info/top_level.txt
pythreadworker-0.10.0.dist-info/zip-safe
pythreadworker-0.10.0.dist-info/RECORD
