Metadata-Version: 2.1
Name: pythreadworker
Version: 0.10.0
Summary: A threading library.
Home-page: https://github.com/eight04/pyWorker
Author: eight
Author-email: eight04@gmail.com
License: MIT
Keywords: thread,threading,worker
Platform: UNKNOWN
Classifier: Development Status :: 5 - Production/Stable
Classifier: Intended Audience :: Developers
Classifier: Topic :: Software Development :: Libraries :: Python Modules
Classifier: License :: OSI Approved :: MIT License
Classifier: Programming Language :: Python :: 3.10
Requires-Python: >=3.10
